starlette_rfc7807/__init__.py
starlette_rfc7807/exception.py
starlette_rfc7807/middleware.py
starlette_rfc7807-0.1.2.dist-info/METADATA
starlette_rfc7807-0.1.2.dist-info/WHEEL
starlette_rfc7807-0.1.2.dist-info/licenses/LICENSE
starlette_rfc7807-0.1.2.dist-info/RECORD
