Metadata-Version: 2.4
Name: starlette-rfc7807
Version: 0.1.2
Summary: Add your description here
License-File: LICENSE
Requires-Python: >=3.11
Requires-Dist: starlette<=1.0,>=0.46.0
